{
  "id": "ec-ley-ley-organica-reformatoria-de-la-ley-orga-10",
  "type": "statute",
  "title": "Ley Orgánica Reformatoria de la Ley Orgánica Electoral y de Organizaciones Políticas de la República del Ecuador, Código de la Democracia",
  "title_en": "Ley Orgánica Reformatoria de la Ley Orgánica Electoral y de Organizaciones Políticas de la República del Ecuador, Código de la Democracia",
  "short_name": "Ley 10",
  "status": "in_force",
  "issued_date": "2025-07-24",
  "in_force_date": "2025-07-24",
  "url": "https://www.asambleanacional.gob.ec/es/system/files/ro_15.pdf",
  "provisions": [
    {
      "provision_ref": "full-text",
      "section": "Ley Orgánica Reformatoria de la Ley Orgánica Electoral y de Organizaciones Políticas de la República del Ecuador, Código de la Democracia",
      "title": "Ley Orgánica Reformatoria de la Ley Orgánica Electoral y de Organizaciones Políticas de la República del Ecuador, Código de la Democracia",
      "content": "El Pleno de la Asamblea Nacional, de conformidad con lo previsto en los artículos 120, numeral 6, de la Constitución de la\n                       República del Ecuador y 9, numeral 6, de la Ley Orgánica de la Función Legislativa, trató el proyecto de “Ley Orgánica\n                       Reformatoria de la Ley Orgánica Electoral y de Organizaciones Políticas de la República del Ecuador, Código de la\n                       Democracia” de acuerdo al siguiente detalle:\n\n                       1.     Primer debate: 25 de enero de 2023;\n                       2.     Segundo debate: 10 y 20 de junio de 2025, en la continuación de la sesión 1024.\n                       3.     Fecha de aprobación: 20 de junio de 2025, en la continuación de la sesión 1024.\n                       4.     Fecha de objeción presidencial: 08 de julio de 2025 (número de trámite 468687);\n                       5.     Fecha de aprobación de la enmienda del proyecto: 21 de julio de 2025, en la sesión Nro. 020-AN-2025-2029.\n\n                       En la sesión Nro. 020-AN-2025-2029 de 21 de julio de 2025, el Pleno de la Asamblea Nacional aprobó el Informe no vinculante de\n                       la Objeción Parcial por Inconveniencia, bajo la siguiente moción:\n\n                       “ALLANAMIENTO RESPECTO A LA OBJECIÓN PARCIAL POR INCONVENIENCIA DEL PROYECTO DE LEY\n                       ORGÁNICA REFORMATORIA DE LA LEY ORGÁNICA ELECTORAL Y DE ORGANIZACIONES POLÍTICAS DE LA\n                       REPÚBLICA DEL ECUADOR, CÓDIGO DE LA DEMOCRACIA.”\n\n                       Por consiguiente, en atención a los artículos 138 de la Constitución de la República del Ecuador y 64 de la Ley Orgánica de la\n                       Función Legislativa, se remite el (i) texto auténtico del proyecto de “Ley Orgánica Reformatoria de la Ley Orgánica Electoral y\n                       de Organizaciones Políticas de la República del Ecuador, Código de la Democracia”; y, (ii) la certificación de la Secretaría\n                       General, respecto de las fechas en las que el Pleno de la Asamblea Nacional realizó el tratamiento del proyecto de ley; para su\n                       publicación en el Registro Oficial.\n\n                       Con sentimientos de distinguida consideración.\n\n                       Atentamente,\n\n                       Documento firmado electrónicamente\n                       Sr. Giovanny Francisco Bravo Rodriguez\n                       SECRETARIO GENERAL\n\n                       Anexos:\n                           - Anexo 1: Ley Orgánica Reformatoria de la Ley Orgánica Electoral y de Organizaciones Políticas de la República del Ecuador, Código de la\n                           Democracia\n                           - Anexo 2: Certificación Secretaría General\n\n                       Copia:\n                            Señor Abogado\n                            Jorge Enrique López Terán\n                            Prosecretario General\n\n                               Señorita Magíster\n\n                                                                                           2                                                                           1/2\n* Documento firmado electrónicamente por DTS 2.0 Producción\n\n                  Oficio Nro. AN-SG-2025-0530-O\n                   Registro Oficial - Segundo Suplemento Nº 88                                             Jueves 24 de julio de 2025\n                  Quito, D.M., 23 de julio de 2025\n\n                               Karla Alejandra Cardenas Bahamontes\n                               Especialista Senior del Despacho Central\n\n                       kc\n\n                                                                          \n                                                                          GIOVANNY FRANCISCO\n                                                                          BRAVO RODRIGUEZ\n                                                                          \n                                                                          \n\n                                                                                                                                        2/2\n* Documento firmado electrónicamente por DTS 2.0 Producción\n\n                                                                          3\n\nJueves 24 de julio de 2025                              Segundo Suplemento Nº 88 - Registro Oficial\n\n \n \n\n                                               \n                                               \n \n                                       \n                                \n\n           \n       “ \n        \n       \n ”\n \n \n     \n     \n        \n     \n        \n     \n     \n        \n \n\n \n \n\n \n                                         \n                                         GIOVANNY FRANCISCO\n                                         BRAVO RODRIGUEZ\n                                         \n                                         \n\n                             \n                                  \n \n \n\n                                            4\n\nRegistro Oficial - Segundo Suplemento Nº 88                              Jueves 24 de julio de 2025\n \n\n \n                                           \n                                       \n \n               \n        \n               \n        \n  \n                 \n                    \n                   \n                    \n        \n               \n        \n        \n        \n               \n                    \n        \n        \n        \n               \n        \n        \n  \n        \n                   \n                  \n                  \n                                                                                   \n \n                                                 5\n\nJueves 24 de julio de 2025                             Segundo Suplemento Nº 88 - Registro Oficial\n\n        \n        \n        \n  \n        \n               \n                 \n                  \n        \n  \n        \n                    \n        \n  \n        \n                    \n        \n  \n                  \n                   \n                     \n        \n                  \n                \n                  \n                     \n        \n  \n                    \n        \n\n                                                                                   \n \n\n                                                 6\n\nRegistro Oficial - Segundo Suplemento Nº 88                             Jueves 24 de julio de 2025\n\n          \n                 \n                 \n                 \n        \n  \n               \n                 \n        \n  \n                 \n        \n                    \n        \n        \n  \n        \n                \n                \n        \n               \n                   \n        \n               \n                  \n        \n        \n        \n        \n                 \n\n                                                                                  \n \n\n                                                7\n\nJueves 24 de julio de 2025                            Segundo Suplemento Nº 88 - Registro Oficial\n\n        \n        \n  \n        \n        \n  \n                 \n        \n                   \n             \n        \n          \n                   \n               \n        \n        \n               \n                  \n            constitucionales relativas a: “1. El sistema\n                 \n        \n                   \n                 \n                   \n                 \n        \n                  \n                   \n        ticia electoral”;\n\n                                                                                  \n \n\n                                                 8\n\nRegistro Oficial - Segundo Suplemento Nº 88                              Jueves 24 de julio de 2025\n\n               \n                   \n                \n        \n  \n        \n        \n                  \n               \n        \n  \n        \n                  \n        \n        \n        \n  \n        \n        \n                    \n        \n        \n  \n                  \n        \n        \n                  \n        \n        \n \n\n                                                                                   \n \n\n                                                 9\n\nJueves 24 de julio de 2025                          Segundo Suplemento Nº 88 - Registro Oficial\n\n \n \n \n                                               \n     \n \n                                        \n                                               \n \n \n\n \n             \n      agregase la frase “político, de no discriminación”:\n\n      \n      \n\n \n      \n      \n\n                    \n               \n               \n               \n                  \n               \n               \n          \n\n      \n               \n      \n      \n\n                                                                               \n \n\n                                              10\n\n    Registro Oficial - Segundo Suplemento Nº 88                          Jueves 24 de julio de 2025\n\n                  \n                     \n                        \n              \n          \n              \n\n     \n     \n                          \n                     \n              \n\n     \n     \n\n                         \n                     \n                     \n                        \n                        \n              \n                         \n                      \n              \n              \n              \n\n                          \n                        \n                      \n                        \n              \n                                                                                 \n\n\n                                                  11\n\n    Jueves 24 de julio de 2025                       Segundo Suplemento Nº 88 - Registro Oficial\n\n\n    \n\n                       \n                      \n             \n                       \n             \n\n           \n    \n\n                      \n             \n             \n                                 \n                     \n             \n\n                      \n             \n                    \n             \n             \n                        \n                     \n             \n                      \n             \n             \n\n                       \n                      \n\n                                                                              \n\n\n                                                12\n\n    Registro Oficial - Segundo Suplemento Nº 88                         Jueves 24 de julio de 2025\n\n              \n              \n\n                         \n                     \n              \n\n             \n                 \n                \n      \n\n                         \n              \n              \n\n              \n      \n\n                      \n                      \n              \n              \n              \n\n              \n              \n              \n                   \n              \n\n              \n                      \n                    \n              \n\n                                                                                \n\n\n                                                  13\n\n    Jueves 24 de julio de 2025                         Segundo Suplemento Nº 88 - Registro Oficial\n\n                        \n             \n             \n             \n\n                     \n                    \n             \n\n                      \n             \n\n\n                 \n    “dignidad” la frase “u opción”.\n\n\n    frase “en un plazo menor a noventa días,”\n    por la frase “en un plazo menor a ciento veinte días,”.\n\n     \n    \n\n                    \n                        \n                         \n                         \n                          \n                          \n                          \n                 \n                 \n             \n                            \n                 \n\n                                                                               \n\n\n                                                 14\n\n    Registro Oficial - Segundo Suplemento Nº 88                         Jueves 24 de julio de 2025\n\n                        \n                \n                \n      \n     \n\n                     \n                      \n              –\n               –         \n                      \n              \n\n              \n              \n              \n              \n\n                     \n                      \n              \n\n                             \n                                      \n                             \n                     \n                             \n                            \n                     \n                     \n                     \n\n                                                                               \n\n\n                                                  15\n\n    Jueves 24 de julio de 2025                        Segundo Suplemento Nº 88 - Registro Oficial\n\n                          \n                  \n                  \n                          \n                  \n                  \n               \n                  \n                  \n                           \n                          \n                  \n               \n                  \n                  \n                        \n                   \n                            \n                  \n                           \n                           \n                  \n                  \n                  \n                  \n                  \n               \n                  \n                          \n                  \n\n                                                                              \n\n\n                                                 16\n\n    Registro Oficial - Segundo Suplemento Nº 88                         Jueves 24 de julio de 2025\n\n                     \n                     \n                              \n                             \n                     \n                              \n                     \n                     \n                            \n                             \n                              \n                            \n                     \n                     \n                             \n                           \n                     \n                     \n                              \n                     \n                            \n                           \n                            \n                             \n                             \n                     \n                     \n                     \n                     \n\n     \n                                                                         \n\n\n                                                  17\n\n    Jueves 24 de julio de 2025                          Segundo Suplemento Nº 88 - Registro Oficial\n\n                      \n                        \n              \n\n\n     \n\n              \n              \n                        \n              \n\n      \n     \n\n              \n              \n                       \n              \n                      \n                        \n              \n\n     \n     \n\n               \n                              \n                  \n\n     \n     \n\n              \n                        \n                       \n                                                                                 \n\n\n                                                  18\n\n    Registro Oficial - Segundo Suplemento Nº 88                       Jueves 24 de julio de 2025\n\n              \n                       \n                       \n              \n\n\n     \n\n              \n                      \n                      \n                      \n              \n\n              \n              \n              \n              \n              \n\n                        \n                        \n                         \n                     \n              \n\n                       \n              \n              \n              \n\n              \n                        \n              \n\n                                                                             \n\n\n                                                  19\n\n    Jueves 24 de julio de 2025                         Segundo Suplemento Nº 88 - Registro Oficial\n\n              \n              \n                       \n              \n              \n              \n\n              \n                     \n              \n\n                      \n              \n              \n              \n\n             \n     \n\n              \n                       \n                       \n              \n                           \n              \n                       \n              \n\n              \n              \n              \n              \n\n                                                                                \n\n\n                                                  20\n\n    Registro Oficial - Segundo Suplemento Nº 88                       Jueves 24 de julio de 2025\n\n              \n                     \n              \n\n              \n              \n\n              \n                       \n                        \n              \n\n\n      \n     público о privado\" por el siguiente texto: “persona natural o jurídica, nacional o\n     extranjera u organismo público o privado,”\n\n     \n     \n\n              \n              \n                         \n                     \n                        \n              \n\n\n     \n\n                       \n                       \n              \n\n                                                                            \n\n\n                                                  21\n\n    Jueves 24 de julio de 2025                        Segundo Suplemento Nº 88 - Registro Oficial\n\n                         \n              \n              \n\n              \n              \n\n              \n              \n\n              "
    }
  ],
  "definitions": []
}