{
  "id": "ec-ley-ley-organica-para-impulsar-la-iniciativa-31",
  "type": "statute",
  "title": "Ley Orgánica para impulsar la iniciativa privada en la generación de energías",
  "title_en": "Ley Orgánica para impulsar la iniciativa privada en la generación de energías",
  "short_name": "Ley 23",
  "status": "in_force",
  "issued_date": "2024-10-28",
  "in_force_date": "2024-10-28",
  "url": "https://www.asambleanacional.gob.ec/es/system/files/ro_ley_publicada.pdf",
  "provisions": [
    {
      "provision_ref": "art1",
      "section": "Ley Orgánica para impulsar la iniciativa privada en la generación de energías",
      "title": "Objeto.- La presente Ley tiene por objeto promover soluciones",
      "content": "Artículo 1.- Objeto.- La presente Ley tiene por objeto promover soluciones\neconómicas y de generación de energía renovable a fin de superar la crisis\nenergética, optimizando el uso de recursos públicos asociados al sector eléctrico e\nincentivar la inversión privada en todo el territorio nacional, priorizando la\ndiversificación de la matriz energética para lograr una transición sostenible y\nresiliente.\n6\nRegistro Oﬁcial - Octavo Suplemento Nº 673                     Lunes 28 de octubre de 2024"
    },
    {
      "provision_ref": "art2",
      "section": "Ley Orgánica para impulsar la iniciativa privada en la generación de energías",
      "title": "Ámbito.- Las disposiciones de la presente Ley, son de carácter",
      "content": "Artículo 2.- Ámbito.- Las disposiciones de la presente Ley, son de carácter\nespecial, de orden público y se aplicarán de forma prioritaria en el sector eléctrico\nen el ámbito público y privado, así como en todo el territorio nacional."
    },
    {
      "provision_ref": "art3",
      "section": "Ley Orgánica para impulsar la iniciativa privada en la generación de energías",
      "title": "Finalidad.- Esta Ley tiene como finalidad fomentar la inversión",
      "content": "Artículo 3.- Finalidad.- Esta Ley tiene como finalidad fomentar la inversión\nprivada en energías limpias, facilitar el desarrollo e implementación de proyectos\nde generación eléctrica de diferentes fuentes de energía renovable y energías de\ntransición, así como, establecer mecanismos de optimización del uso de energía\neléctrica en los sectores público y privado, optimizar el uso de recursos estatales y\ngarantizar el servicio de energía eléctrica de manera estable y accesible en todo el\nterritorio nacional.\nDISPOSICIONES GENERALES\nPRIMERA.- Las personas jurídicas dedicadas a la actividad de generación térmica\ndeberán presentar planes de transición hacia tecnologías de menor impacto\nambiental, como el uso de gas natural en lugar de combustibles fósiles más\ncontaminantes, y desarrollar proyectos híbridos que combinen generación térmica\ncon energías renovables.\nEl Ministerio del ramo en materia de energía facilitará la obtención de licencias\ncoordinando las acciones necesarias con el Ministerio de Ambiente, Agua y\nTransición Ecológica y otras entidades competentes, para generar procesos más\ncortos, no duplicación de requisitos, el uso de tecnologías de información y otras\ndisponibles para acelerar la emisión de las licencias e importación, explotación y\naprovechamiento de gas natural.\nSEGUNDA.- Las personas jurídicas legalmente domiciliadas o establecidas en el\npaís podrán importar gas natural siempre y cuando tengan los siguientes objetivos;\npara autoconsumo para procesos productivos, así como aquellos que tengan como\nfin generar energía eléctrica y sustituir el uso de otros hidrocarburos en actividades\nproductivas realizadas dentro del país, contribuyendo a través de esta iniciativa\n7\nLunes 28 de octubre de 2024                     Octavo Suplemento Nº 673 - Registro Oﬁcial\nprivada a resolver la escasez energética y a disminuir la demanda de dichos\ncombustibles. Esta importación deberá sujetarse a los requisitos técnicos, normas\nde calidad y control que fije la Agencia de Regulación y Control del sector.\nTERCERA.- Los proyectos actualmente en trámite con límites de 10 MW podrán\nsolicitar una revisión de sus permisos para adaptarse a los nuevos límites de\npotencia, conforme a los procedimientos que dictamine el Ministerio de Ramo.\nCUARTA.- Los proyectos que actualmente operan bajo el límite de 10 MW podrán\nsolicitar un ajuste de potencia conforme a los nuevos criterios establecidos, previa\nevaluación técnica que garantice su viabilidad.\nQUINTA.- El Ministerio de Ramo deberá incluir en todos los contratos que celebre\ncon entidades públicas o privadas cláusulas de estabilidad jurídica, las cuales\ngarantizarán la inalterabilidad de las condiciones legales aplicables durante la\nvigencia del contrato. Estas cláusulas deberán considerar los tributos centrales y\nseccionales vigentes al momento de la suscripción del contrato.\nSEXTA.- Los Gobiernos Autónomos Descentralizados deberán implementar\nsistemas de gestión de residuos que incluyan el procesamiento de basura para la\ngeneración de energía. Esta energía podrá ser vendida al Sistema Nacional\nInterconectado de conformidad con lo establecido por el artículo 52 de la Ley\nOrgánica del Servicio Público de Energía Eléctrica.\nSÉPTIMA.-     Se dispone a las Empresas Eléctricas Distribuidoras la ejecución\nprogresiva del plan de renovación de alumbrado público emitido por el Ministerio\nde ramo en materia de Electricidad para el reemplazo de las luminarias públicas\nactuales por luminarias de tecnología LED y solares.\nOCTAVA.- La banca pública y privada podrá incorporar dentro de su oferta de\nproductos financieros, créditos con tasas preferenciales destinados a personas\nnaturales y jurídicas del sector privado que deseen implementar sistemas de\ngeneración de energía a partir de fuentes renovables para autoconsumo. Estos\n8\nRegistro Oﬁcial - Octavo Suplemento Nº 673                   Lunes 28 de octubre de 2024\nsistemas deberán permitir a los beneficiarios la posibilidad de comercializar\ncualquier excedente de energía generado, de conformidad con la normativa vigente\ny los procedimientos establecidos por las autoridades competentes.\nDISPOSICIONES TRANSITORIAS\nPRIMERA.- En el término máximo de 30 días contados desde la entrada en vigencia\nde esta Ley, la Agencia de Regulación y Control de Energía Eléctrica, el Ministerio\ndel Ramo y las empresas del servicio público de energía eléctrica emitirán las\nregulaciones y/o procedimientos requeridos para la eficiente implementación de\nlas reformas derivadas de la presente Ley.\nSEGUNDA.- El Ministerio de Ambiente Agua y Transición Ecológica emitirá los\nrespectivos certificados ambientales, licencias y/o cualquier permiso ambiental\nque se requiera para la implementación de los proyectos derivados de la presente\nLey previo el cumplimiento de los requisitos constitucionales y legales.\nTERCERA.- La Agencia de Regulación y Control de Hidrocarburos y el Ministerio\nSectorial emitirán en el plazo máximo de (30) días, las respectivas regulaciones y/o\ninstructivos que permitan la importación de gas natural a quienes requieran su\nutilización para los proyectos de generación y/o autogeneración derivados de la\npresente Ley.\nCUARTA.- En el plazo máximo de treinta (30) días contados a partir de la\npublicación de esta Ley, las distribuidoras firmarán los Contratos Regulados con\nlos Concesionarios a quienes se adjudicaron los proyectos previstos en el Plan\nMaestro de Electricidad, siempre que cuenten con el respectivo contrato de\nconcesión.\nQUINTA.- En el plazo máximo de tres (3) meses el Ministerio de Energía y Minas\nen coordinación con Petroecuador convocará a concurso los proyectos de\nexplotación y repotenciación de los campos identificados de gas natural.\n9\nLunes 28 de octubre de 2024                        Octavo Suplemento Nº 673 - Registro Oﬁcial\nDISPOSICIONES REFORMATORIAS\nPRIMERA: En la Ley Orgánica del Servicio Público de Energía Eléctrica efectúese\nlas siguientes reformas:\nUno.- Agréguese en el artículo 3, los siguientes numerales:\n“22. Generación de transición: Son tecnologías de generación no renovable de\nbajo impacto ambiental, tal que permitan la transición gradual de la matriz\nenergética.\n23. Potenciación: Mejorar, fortalecer u optimizar los activos y equipos\neléctricos para aumentar su eficiencia, confiabilidad y capacidad de\nproducción.    Esto    puede     implicar   la   modernización   de   equipos,   la\nactualización de tecnología obsoleta, la mejora de la capacidad de transmisión\ny distribución o la implementación de medidas para prevenir fallas y asegurar\nun suministro eléctrico constante y seguro.\n24. Consumidor Regulado: Persona natural o jurídica que, mediante la\nsuscripción de un contrato de suministro, se beneficia con la prestación del\nservicio público de energía eléctrica y del servicio de alumbrado público\ngeneral, bien como propietario del inmueble en donde éste se presta, o como\nreceptor directo del servicio.\n25. Consumidor No Regulado: Persona jurídica autorizada para conectar sus\ninstalaciones a la red de distribución o de transmisión, mediante la\nsuscripción de un contrato de conexión, a fin de abastecer sus requerimientos\nde energía y de potencia. Esta persona jurídica puede ser un Gran\nConsumidor o un Consumo Propio de un autogenerador.\n26. Demanda regulada: Demanda de potencia y consumo de energía de los\nusuarios finales. Incluye el consumo del alumbrado público general. No\nconsidera la demanda de los consumos propios de autogeneradores ni la de\n10\nRegistro Oﬁcial - Octavo Suplemento Nº 673                    Lunes 28 de octubre de 2024\nlos grandes consumidores que hayan suscrito contratos bilaterales con\nautogeneradores o generadores.”\nDos.- Agréguese a continuación del inciso final del artículo 29, el siguiente inciso:\n“Estos contratos podrán estar respaldados por garantías que pueda establecer\nel Estado a fin de asegurar el repago de las obligaciones contractuales. El\nReglamento a esta Ley determinará las formas de garantía y, previo a su\nestablecimiento, se requerirá el pronunciamiento favorable del ente rector de\nlas finanzas públicas.”\nTres.- Agréguese a continuación del inciso tercero del artículo 33, el siguiente\ninciso:\n“Se excluye de esta obligación de reversión, los bienes instalados por el\nusuario final para su autoabastecimiento; a los autogeneradores; a los\ncogeneradores;    y de aquellos generadores de energía renovable no\nconvencional de hasta 10 MW.”\nCuatro.- Agréguese a continuación del inciso final del artículo 40, el siguiente\ninciso:\n“Para proyectos de generación identificados por la iniciativa privada, que no\nse encuentren dentro del Plan Maestro de Electricidad, el proponente tendrá\nderecho a mejorar la oferta cuando se presenten otros oferentes en el proceso\npúblico de selección.”\nCinco.- Agréguese a continuación del artículo 49, el siguiente artículo innumerado:\n“Art. (…). - El cobro y pago de las obligaciones derivadas de las transacciones\ncomerciales de la demanda regulada, se realizará conforme el orden de\nprelación, definido por la ARCONEL a través de regulación. Para el efecto, las\nempresas de distribución podrán constituir un fideicomiso con el aporte de la\nrecaudación del usuario final por concepto del servicio público de energía\n11\nLunes 28 de octubre de 2024                      Octavo Suplemento Nº 673 - Registro Oﬁcial\neléctrica y alumbrado público general, que aseguren el cumplimiento del\norden de prelación establecido, observando lo previsto en esta Ley y en la\nnormativa expedida por la ARCONEL y el Ministerio del Ramo. La recaudación\nfideicomitida no incluirá los pagos y cobros que se recauden por cuenta de\nterceros, tales como las tasas de recolección de basura y aseo público, y\ncualquier otro valor que se recaude por conceptos distintos al servicio público\nde energía eléctrica; estos valores deberán ser entregados en su integridad a\nla empresa de distribución que corresponda, para que realice los pagos a su\ntitular de conformidad con la Ley.”\nSeis.- Sustitúyese el artículo 52 por el siguiente:\n“Artículo 52.- De los procesos públicos de selección.- Para la construcción,\noperación y mantenimiento de proyectos prioritarios, según el orden de\nejecución previsto en el Plan Maestro de Electricidad (PME), que podrían ser\nconcesionados a empresas públicas, empresas privadas o de economía\npopular y solidaria, el Ministerio del Ramo efectuará procesos públicos de\nselección.\nEl oferente que resultare seleccionado del proceso público tiene el derecho a\nque se le otorgue el título habilitante respectivo. En los procesos públicos de\nselección, se priorizarán aquellos proyectos que se encuentren identificados\nen zona de frontera.\nPosterior a la suscripción del título habilitante, el concesionario deberá\nsuscribir los contratos respectivos, sobre la base de las condiciones\nresultantes del proceso de selección y la normativa aplicable.\nCuando los proyectos sean identificados por la iniciativa privada y no estén\nincorporados en el Plan Maestro de Electricidad (PME), lo podrá desarrollar,\na su riesgo, previa expresa autorización del Ministerio de Ramo quien deberá\nverificar la capacidad técnica, económica, jurídica y demás que se establezcan\n12\nRegistro Oﬁcial - Octavo Suplemento Nº 673                       Lunes 28 de octubre de 2024\nen el Reglamento y siempre que su potencia no supere los 100 MW en\nproyectos de energía renovable no convencional y 100 MW en proyectos de\nenergía de transición.\nSi los proyectos de iniciativa privada superan los 100 MW en proyectos de\nenergía renovable no convencional y 100MW en proyectos de energía de\ntransición, su desarrollo se sujetará a un proceso público de selección. El\nEstado le otorgará al promotor del proyecto los beneficios para su\nparticipación en el proceso público de selección, establecidos en la normativa\naplicable.\nEn el proceso de construcción, operación y mantenimiento, de aquellos\nproyectos que sean identificados por la iniciativa privada y no consten en el\nPME, y por ende que no sean resultado de un PPS, se dará prioridad y precio\npreferente a proyectos que promuevan el uso de tecnologías limpias y energía\nrenovable no convencional que posea capacidad de almacenamiento,\ninclusión de redes de interconexión a la red eléctrica (transmisión), que sean\nde hasta 100MW y proyectos de energía de transición de hasta 100MW, de\nconformidad con lo estipulado por la Agencia de Regulación y Control.\nÚnicamente se dará despacho y precio preferente a aquellos proyectos ERNC\nde hasta 10MW.\nAl final del plazo de la concesión la infraestructura implementada en estos\nproyectos será revertida al Estado sin costo alguno.”\nSiete.- En el artículo 56, realícese los siguientes cambios:\n1.Elimínese la oración final del quinto inciso:\n“En ambos casos, los criterios de asignación a proyectos de desarrollo\nterritorial, así como el periodo de asignación, serán determinados en el\nreglamento general de aplicación a esta Ley.”\n13\nLunes 28 de octubre de 2024                      Octavo Suplemento Nº 673 - Registro Oﬁcial\n2. A continuación del quinto inciso agréguese el siguiente:\n“Los fondos provenientes de generadores públicos, así como los recursos\nprovenientes de empresas privadas, serán ejecutados directamente por los\nGAD para lo cual las empresas generadoras deberán acreditar los valores\nestipulados al Ministerio de Economía y Finanzas quien a su vez realizará las\ntransferencias a los GAD en el ejercicio fiscal en que los reciba. La distribución\nde los recursos entre los GAD seguirá los siguientes criterios:\ni) 45% para los GAD provinciales del área de influencia.\nii) 35% para los GAD cantonales del área de influencia.\niii) 20% para los GAD parroquiales rurales del área de influencia.\nEstos recursos serán destinados exclusivamente para gastos de inversión.”\nOcho.- Agréguese después del último párrafo del Artículo 67 el siguiente texto:\n“Las infracciones antes señaladas y su correspondiente sanción, también\nserán aplicables a la Agencia de Regulación y Control de Electricidad –\nARCONEL, en lo que fuere pertinente y corresponderá al Ministerio rector su\nvaloración y aplicación.”\nNueve.- Agréguese después del literal k) del Artículo 68 el siguiente literal l):\n“l) Mantener de manera reiterada e injustificada elevados niveles de\nindisponibilidad de los recursos de generación y transmisión que afecten el\nabastecimiento de la demanda en cantidad o en condiciones de economía.”\nDiez.- Sustitúyese el segundo inciso de la Disposición General Sexta, por el\nsiguiente:\n“El titular del título habilitante producto de un PPS tendrá derecho a utilizar\ntodos los mecanismos previstos en el ordenamiento jurídico vigente, a fin de\ngarantizar el pago a sus financistas o acreedores garantizados. Los financistas\n14\nRegistro Oﬁcial - Octavo Suplemento Nº 673                                        Lunes 28 de octubre de 2024\nacreedores garantizados podrán a su vez, suscribir acuerdos directos con la\nentidad concedente, a fin de asegurar la continuidad del proyecto, se\nreconocerán los derechos de intervención que estarán previstos en el\nreglamento. Bajo ninguna circunstancia se suspenderá la ejecución de un\nproyecto surgido de un PPS para la prestación del servicio público de energía\neléctrica.”"
    },
    {
      "provision_ref": "disposicion-final-unica",
      "section": "Ley Orgánica para impulsar la iniciativa privada en la generación de energías",
      "title": "La presente Ley entrará en vigor a partir de su publicación en el Registro",
      "content": "DISPOSICIÓN FINAL\nÚNICA.- La presente Ley entrará en vigor a partir de su publicación en el Registro\nOficial.\nDada y suscrita en la sede de la Asamblea Nacional, ubicada en el Distrito\nMetropolitano de Quito, provincia de Pichincha a los veintisiete días del mes de\noctubre del año dos mil veinticuatro.\nFirmado electrónicamente por:\nREBECA VIVIANA\nVELOZ RAMIREZ\nVIVIANA VELOZ R.\nPresidenta de la Asamblea Nacional\nFirmado electrónicamente por:\nALEJANDRO XAVIER\nMUNOZ HIDALGO\nABG. ALEJANDRO MUÑOZ HIDALGO\nSecretario General\n15\nLunes 28 de octubre de 2024                                 Octavo Suplemento Nº 673 - Registro Oﬁcial\nDADO EN LA CIUDAD DE GUAQUIL, VEINTISIETE DE OCTUBRE DE DOS MIL\nVEINTICUATRO.\nSANCIÓNESE Y PROMÚLGUESE\nFirmado electrónicamente por:\nDANIEL ROYGILCHRIST\nNOBOA AZIN\nDaniel Noboa Azín\nPRESIDENTE CONSTITUCIONAL DE LA REPÚBLICA\nEs fiel copia del original.- Lo Certifico.\nQuito, 27 de octubre de 2024.\nFirmado electrónicamente por:\nSTALIN SANTIAGO\nANDINO GONZALEZ\nMgs. Stalin S. Andino González\nSECRETARIO GENERAL JURÍDICO\nDE LA PRESIDENCIA, ENCARGADO.\n16\nAbg. Jaqueline Vargas Camacho\nDIRECTORA (E)\nQuito:\nCalle Mañosca 201 y Av. 10 de Agosto\nAtención ciudadana\nTelf.: 3941-800\nExts.: 3133 - 3134\nwww.registroficial.gob.ec\nNGAPC\nEl Pleno de la Corte Constitucional mediante Resolución Administrativa No. 010-AD-CC-2019,\nresolvió la gratuidad de la publicación virtual del Registro Oficial y sus productos, así como la\neliminación de su publicación en sustrato papel, como un derecho de acceso gratuito de la\ninformación a la ciudadanía ecuatoriana.\n“Al servicio del país desde el 1º de julio de 1895”\nEl Registro Oficial no se responsabiliza por los errores\nortográficos, gramaticales, de fondo y/o de forma que\ncontengan los documentos publicados, dichos documentos\nremitidos por las diferentes instituciones para su publicación,\nson transcritos fielmente a sus originales, los mismos que\nse encuentran archivados y son nuestro respaldo."
    }
  ],
  "definitions": []
}